pygments_clean.py
pygments_lexer_clean-1.0.5.dist-info/DESCRIPTION.rst
pygments_lexer_clean-1.0.5.dist-info/METADATA
pygments_lexer_clean-1.0.5.dist-info/RECORD
pygments_lexer_clean-1.0.5.dist-info/WHEEL
pygments_lexer_clean-1.0.5.dist-info/metadata.json
pygments_lexer_clean-1.0.5.dist-info/top_level.txt
