Metadata-Version: 2.0
Name: pygments-lexer-clean
Version: 1.0.5
Summary: A Pygments lexer for the Clean language
Home-page: https://gitlab.science.ru.nl/cloogle/pygments-lexer-clean
Author: Camil Staps
Author-email: info@camilstaps.nl
License: MIT
Keywords: syntax highlighting clean pygments
Platform: UNKNOWN
Classifier: Development Status :: 5 - Production/Stable
Classifier: Intended Audience :: Developers
Classifier: Intended Audience :: Information Technology
Classifier: Intended Audience :: Science/Research
Classifier: License :: OSI Approved :: MIT License
Classifier: Operating System :: OS Independent
Classifier: Programming Language :: Python
Classifier: Programming Language :: Python :: 2
Classifier: Programming Language :: Python :: 3
Classifier: Topic :: Text Processing :: Filters
Classifier: Topic :: Utilities
